module_test_poetry/UUID.py
module_test_poetry/__init__.py
module_test_poetry-1.0.0.dist-info/WHEEL
module_test_poetry-1.0.0.dist-info/METADATA
module_test_poetry-1.0.0.dist-info/RECORD
