Metadata-Version: 2.1
Name: module-test-poetry
Version: 1.0.0
Summary: 
Author: Damiano Carradori
Author-email: carradori@igenius.ai
Requires-Python: >=3.7,<4.0
Classifier: Programming Language :: Python :: 3
Classifier: Programming Language :: Python :: 3.7
Classifier: Programming Language :: Python :: 3.8
Requires-Dist: ulid-py (>=0.1.0,<0.2.0)
